simplified_scrapy/__init__.py
simplified_scrapy/core/__init__.py
simplified_scrapy/core/config_helper.py
simplified_scrapy/core/cookie_store.py
simplified_scrapy/core/cookiestroe_base.py
simplified_scrapy/core/dictex.py
simplified_scrapy/core/dns_cache.py
simplified_scrapy/core/html_store.py
simplified_scrapy/core/htmlstore_base.py
simplified_scrapy/core/http_server.py
simplified_scrapy/core/listex.py
simplified_scrapy/core/logex.py
simplified_scrapy/core/mem_cookiestore.py
simplified_scrapy/core/mongo_htmlstore.py
simplified_scrapy/core/mongo_objstore.py
simplified_scrapy/core/mongo_urlstore.py
simplified_scrapy/core/mssql_objstore.py
simplified_scrapy/core/mysql_objstore.py
simplified_scrapy/core/obj_store.py
simplified_scrapy/core/objstore_base.py
simplified_scrapy/core/redis_urlstore.py
simplified_scrapy/core/regex_dic.py
simplified_scrapy/core/regex_helper.py
simplified_scrapy/core/request_helper.py
simplified_scrapy/core/requesttm_base.py
simplified_scrapy/core/spider.py
simplified_scrapy/core/sqlite_cookiestore.py
simplified_scrapy/core/sqlite_htmlstore.py
simplified_scrapy/core/sqlite_requesttm.py
simplified_scrapy/core/sqlite_urlstore.py
simplified_scrapy/core/url_store.py
simplified_scrapy/core/urlstore_base.py
simplified_scrapy/core/utils.py
simplified_scrapy/core/xml_helper.py
simplified_scrapy/core/zip_helper.py
simplified_scrapy/dictex.py
simplified_scrapy/downloader.py
simplified_scrapy/extracter.py
simplified_scrapy/request.py
simplified_scrapy/simplified_doc.py
simplified_scrapy/simplified_main.py
simplified_scrapy/spider.py
simplified_scrapy/this.py
simplified_scrapy-2.0.1.dist-info/METADATA
simplified_scrapy-2.0.1.dist-info/WHEEL
simplified_scrapy-2.0.1.dist-info/licenses/LICENSE
simplified_scrapy-2.0.1.dist-info/RECORD
